<?xml version="1.0" encoding="UTF-8"?>
<!-- Created with TexturePacker http://www.codeandweb.com/texturepacker-->
<!-- $TexturePacker:SmartUpdate:37519814c17dcab93d7190c381b06286:c07168d9521802cd67ed9c8173d8dc3d:23926442eb9951897cfc32bd9c2e4ee4$ -->
<TextureAtlas imagePath="player_shadow.png">
    <SubTexture name="shadow_idle/idle_0000" x="843" y="652" width="103" height="128" frameX="-5" frameY="-7" frameWidth="113" frameHeight="135"/>
    <SubTexture name="shadow_idle/idle_0001" x="1053" y="132" width="102" height="128" frameX="-6" frameY="-7" frameWidth="113" frameHeight="135"/>
    <SubTexture name="shadow_idle/idle_0002" x="1054" y="782" width="102" height="128" frameX="-6" frameY="-7" frameWidth="113" frameHeight="135"/>
    <SubTexture name="shadow_idle/idle_0003" x="1052" y="652" width="102" height="128" frameX="-6" frameY="-7" frameWidth="113" frameHeight="135"/>
    <SubTexture name="shadow_idle/idle_0004" x="1052" y="522" width="102" height="128" frameX="-6" frameY="-7" frameWidth="113" frameHeight="135"/>
    <SubTexture name="shadow_idle/idle_0005" x="949" y="392" width="102" height="128" frameX="-7" frameY="-7" frameWidth="113" frameHeight="135"/>
    <SubTexture name="shadow_idle/idle_0006" x="949" y="262" width="102" height="128" frameX="-7" frameY="-7" frameWidth="113" frameHeight="135"/>
    <SubTexture name="shadow_idle/idle_0007" x="843" y="522" width="103" height="128" frameX="-6" frameY="-7" frameWidth="113" frameHeight="135"/>
    <SubTexture name="shadow_idle/idle_0008" x="740" y="392" width="103" height="128" frameX="-6" frameY="-7" frameWidth="113" frameHeight="135"/>
    <SubTexture name="shadow_idle/idle_0009" x="740" y="262" width="103" height="128" frameX="-7" frameY="-7" frameWidth="113" frameHeight="135"/>
    <SubTexture name="shadow_idle/idle_0010" x="843" y="2" width="103" height="128" frameX="-7" frameY="-7" frameWidth="113" frameHeight="135"/>
    <SubTexture name="shadow_idle/idle_0011" x="740" y="132" width="103" height="128" frameX="-7" frameY="-7" frameWidth="113" frameHeight="135"/>
    <SubTexture name="shadow_idle/idle_0012" x="527" y="658" width="103" height="129" frameX="-6" frameY="-6" frameWidth="113" frameHeight="135"/>
    <SubTexture name="shadow_idle/idle_0013" x="425" y="264" width="102" height="129" frameX="-6" frameY="-6" frameWidth="113" frameHeight="135"/>
    <SubTexture name="shadow_idle/idle_0014" x="424" y="396" width="103" height="129" frameX="-5" frameY="-6" frameWidth="113" frameHeight="135"/>
    <SubTexture name="shadow_idle/idle_0015" x="423" y="527" width="103" height="129" frameX="-5" frameY="-6" frameWidth="113" frameHeight="135"/>
    <SubTexture name="shadow_idle/idle_0016" x="318" y="530" width="103" height="130" frameX="-5" frameY="-5" frameWidth="113" frameHeight="135"/>
    <SubTexture name="shadow_idle/idle_0017" x="213" y="398" width="104" height="130" frameX="-4" frameY="-5" frameWidth="113" frameHeight="135"/>
    <SubTexture name="shadow_idle/idle_0018" x="213" y="266" width="104" height="130" frameX="-4" frameY="-5" frameWidth="113" frameHeight="135"/>
    <SubTexture name="shadow_idle/idle_0019" x="317" y="2" width="104" height="130" frameX="-4" frameY="-5" frameWidth="113" frameHeight="135"/>
    <SubTexture name="shadow_idle/idle_0020" x="213" y="134" width="104" height="130" frameX="-4" frameY="-5" frameWidth="113" frameHeight="135"/>
    <SubTexture name="shadow_idle/idle_0021" x="107" y="402" width="104" height="130" frameX="-4" frameY="-5" frameWidth="113" frameHeight="135"/>
    <SubTexture name="shadow_idle/idle_0022" x="107" y="270" width="104" height="130" frameX="-4" frameY="-5" frameWidth="113" frameHeight="135"/>
    <SubTexture name="shadow_idle/idle_0023" x="211" y="2" width="104" height="130" frameX="-4" frameY="-5" frameWidth="113" frameHeight="135"/>
    <SubTexture name="shadow_idle/idle_0024" x="319" y="265" width="104" height="129" frameX="-4" frameY="-6" frameWidth="113" frameHeight="135"/>
    <SubTexture name="shadow_idle/idle_0025" x="423" y="2" width="104" height="129" frameX="-5" frameY="-6" frameWidth="113" frameHeight="135"/>
    <SubTexture name="shadow_idle/idle_0026" x="319" y="134" width="104" height="129" frameX="-5" frameY="-6" frameWidth="113" frameHeight="135"/>
    <SubTexture name="shadow_idle/idle_0027" x="425" y="793" width="104" height="129" frameX="-5" frameY="-6" frameWidth="113" frameHeight="135"/>
    <SubTexture name="shadow_idle/idle_0028" x="421" y="662" width="104" height="129" frameX="-5" frameY="-6" frameWidth="113" frameHeight="135"/>
    <SubTexture name="shadow_idle/idle_0029" x="319" y="794" width="104" height="129" frameX="-5" frameY="-6" frameWidth="113" frameHeight="135"/>
    <SubTexture name="shadow_idle/idle_0030" x="635" y="783" width="104" height="128" frameX="-6" frameY="-7" frameWidth="113" frameHeight="135"/>
    <SubTexture name="shadow_idle/idle_0031" x="632" y="653" width="104" height="128" frameX="-6" frameY="-7" frameWidth="113" frameHeight="135"/>
    <SubTexture name="shadow_idle/idle_0032" x="632" y="523" width="104" height="128" frameX="-6" frameY="-7" frameWidth="113" frameHeight="135"/>
    <SubTexture name="shadow_idle/idle_0033" x="529" y="393" width="104" height="128" frameX="-6" frameY="-7" frameWidth="113" frameHeight="135"/>
    <SubTexture name="shadow_idle/idle_0034" x="529" y="263" width="104" height="128" frameX="-6" frameY="-7" frameWidth="113" frameHeight="135"/>
    <SubTexture name="shadow_idle/idle_0035" x="632" y="2" width="104" height="128" frameX="-5" frameY="-7" frameWidth="113" frameHeight="135"/>
    <SubTexture name="shadow_idle/idle_0036" x="529" y="133" width="104" height="128" frameX="-5" frameY="-7" frameWidth="113" frameHeight="135"/>
    <SubTexture name="shadow_idle/idle_0037" x="741" y="782" width="103" height="128" frameX="-6" frameY="-7" frameWidth="113" frameHeight="135"/>
    <SubTexture name="shadow_idle/idle_0038" x="738" y="652" width="103" height="128" frameX="-6" frameY="-7" frameWidth="113" frameHeight="135"/>
    <SubTexture name="shadow_idle/idle_0039" x="738" y="522" width="103" height="128" frameX="-5" frameY="-7" frameWidth="113" frameHeight="135"/>
    <SubTexture name="shadow_idle/idle_0040" x="635" y="392" width="103" height="128" frameX="-5" frameY="-7" frameWidth="113" frameHeight="135"/>
    <SubTexture name="shadow_idle/idle_0041" x="635" y="262" width="103" height="128" frameX="-5" frameY="-7" frameWidth="113" frameHeight="135"/>
    <SubTexture name="shadow_idle/idle_0042" x="1052" y="2" width="102" height="128" frameX="-6" frameY="-7" frameWidth="113" frameHeight="135"/>
    <SubTexture name="shadow_idle/idle_0043" x="738" y="2" width="103" height="128" frameX="-5" frameY="-7" frameWidth="113" frameHeight="135"/>
    <SubTexture name="shadow_idle/idle_0044" x="843" y="652" width="103" height="128" frameX="-5" frameY="-7" frameWidth="113" frameHeight="135"/>
    <SubTexture name="shadow_walk/walk_0000" x="635" y="132" width="103" height="128" frameX="-5" frameY="-7" frameWidth="113" frameHeight="135"/>
    <SubTexture name="shadow_walk/walk_0001" x="949" y="132" width="102" height="128" frameX="-6" frameY="-7" frameWidth="113" frameHeight="135"/>
    <SubTexture name="shadow_walk/walk_0002" x="950" y="782" width="102" height="128" frameX="-6" frameY="-7" frameWidth="113" frameHeight="135"/>
    <SubTexture name="shadow_walk/walk_0003" x="948" y="652" width="102" height="128" frameX="-5" frameY="-7" frameWidth="113" frameHeight="135"/>
    <SubTexture name="shadow_walk/walk_0004" x="948" y="522" width="102" height="128" frameX="-5" frameY="-7" frameWidth="113" frameHeight="135"/>
    <SubTexture name="shadow_walk/walk_0005" x="425" y="133" width="102" height="129" frameX="-5" frameY="-6" frameWidth="113" frameHeight="135"/>
    <SubTexture name="shadow_walk/walk_0006" x="531" y="789" width="102" height="129" frameX="-5" frameY="-6" frameWidth="113" frameHeight="135"/>
    <SubTexture name="shadow_walk/walk_0007" x="528" y="527" width="102" height="129" frameX="-5" frameY="-6" frameWidth="113" frameHeight="135"/>
    <SubTexture name="shadow_walk/walk_0008" x="319" y="396" width="103" height="129" frameX="-4" frameY="-6" frameWidth="113" frameHeight="135"/>
    <SubTexture name="shadow_walk/walk_0009" x="213" y="530" width="103" height="130" frameX="-3" frameY="-5" frameWidth="113" frameHeight="135"/>
    <SubTexture name="shadow_walk/walk_0010" x="107" y="137" width="104" height="131" frameX="-2" frameY="-4" frameWidth="113" frameHeight="135"/>
    <SubTexture name="shadow_walk/walk_0011" x="213" y="809" width="104" height="131" frameX="-2" frameY="-4" frameWidth="113" frameHeight="135"/>
    <SubTexture name="shadow_walk/walk_0012" x="212" y="676" width="104" height="131" frameX="-2" frameY="-4" frameWidth="113" frameHeight="135"/>
    <SubTexture name="shadow_walk/walk_0013" x="106" y="542" width="105" height="132" frameX="-1" frameY="-3" frameWidth="113" frameHeight="135"/>
    <SubTexture name="shadow_walk/walk_0014" x="2" y="812" width="105" height="132" frameX="-1" frameY="-3" frameWidth="113" frameHeight="135"/>
    <SubTexture name="shadow_walk/walk_0015" x="106" y="676" width="104" height="132" frameX="-1" frameY="-3" frameWidth="113" frameHeight="135"/>
    <SubTexture name="shadow_walk/walk_0016" x="2" y="2" width="104" height="133" frameX="0" frameY="-2" frameWidth="113" frameHeight="135"/>
    <SubTexture name="shadow_walk/walk_0017" x="2" y="407" width="103" height="133" frameX="-1" frameY="-2" frameWidth="113" frameHeight="135"/>
    <SubTexture name="shadow_walk/walk_0018" x="2" y="272" width="103" height="133" frameX="0" frameY="-2" frameWidth="113" frameHeight="135"/>
    <SubTexture name="shadow_walk/walk_0019" x="2" y="137" width="103" height="133" frameX="0" frameY="-2" frameWidth="113" frameHeight="135"/>
    <SubTexture name="shadow_walk/walk_0020" x="2" y="677" width="102" height="133" frameX="0" frameY="-2" frameWidth="113" frameHeight="135"/>
    <SubTexture name="shadow_walk/walk_0021" x="2" y="542" width="102" height="133" frameX="0" frameY="-2" frameWidth="113" frameHeight="135"/>
    <SubTexture name="shadow_walk/walk_0022" x="109" y="810" width="102" height="132" frameX="-2" frameY="-3" frameWidth="113" frameHeight="135"/>
    <SubTexture name="shadow_walk/walk_0023" x="108" y="2" width="101" height="131" frameX="-5" frameY="-4" frameWidth="113" frameHeight="135"/>
    <SubTexture name="shadow_walk/walk_0024" x="318" y="662" width="101" height="130" frameX="-6" frameY="-5" frameWidth="113" frameHeight="135"/>
    <SubTexture name="shadow_walk/walk_0025" x="529" y="2" width="101" height="129" frameX="-7" frameY="-6" frameWidth="113" frameHeight="135"/>
    <SubTexture name="shadow_walk/walk_0026" x="1156" y="2" width="101" height="128" frameX="-8" frameY="-7" frameWidth="113" frameHeight="135"/>
    <SubTexture name="shadow_walk/walk_0027" x="1157" y="261" width="101" height="127" frameX="-8" frameY="-8" frameWidth="113" frameHeight="135"/>
    <SubTexture name="shadow_walk/walk_0028" x="1259" y="2" width="101" height="127" frameX="-8" frameY="-8" frameWidth="113" frameHeight="135"/>
    <SubTexture name="shadow_walk/walk_0029" x="1157" y="132" width="101" height="127" frameX="-8" frameY="-8" frameWidth="113" frameHeight="135"/>
    <SubTexture name="shadow_walk/walk_0030" x="1260" y="646" width="102" height="126" frameX="-8" frameY="-9" frameWidth="113" frameHeight="135"/>
    <SubTexture name="shadow_walk/walk_0031" x="1261" y="387" width="102" height="126" frameX="-8" frameY="-9" frameWidth="113" frameHeight="135"/>
    <SubTexture name="shadow_walk/walk_0032" x="1260" y="518" width="102" height="126" frameX="-8" frameY="-9" frameWidth="113" frameHeight="135"/>
    <SubTexture name="shadow_walk/walk_0033" x="1260" y="259" width="102" height="126" frameX="-8" frameY="-9" frameWidth="113" frameHeight="135"/>
    <SubTexture name="shadow_walk/walk_0034" x="1362" y="2" width="102" height="126" frameX="-8" frameY="-9" frameWidth="113" frameHeight="135"/>
    <SubTexture name="shadow_walk/walk_0035" x="1364" y="130" width="102" height="125" frameX="-8" frameY="-10" frameWidth="113" frameHeight="135"/>
    <SubTexture name="shadow_walk/walk_0036" x="1260" y="131" width="102" height="126" frameX="-8" frameY="-9" frameWidth="113" frameHeight="135"/>
    <SubTexture name="shadow_walk/walk_0037" x="1157" y="390" width="102" height="126" frameX="-7" frameY="-9" frameWidth="113" frameHeight="135"/>
    <SubTexture name="shadow_walk/walk_0038" x="1262" y="774" width="101" height="126" frameX="-8" frameY="-9" frameWidth="113" frameHeight="135"/>
    <SubTexture name="shadow_walk/walk_0039" x="1158" y="778" width="102" height="127" frameX="-7" frameY="-8" frameWidth="113" frameHeight="135"/>
    <SubTexture name="shadow_walk/walk_0040" x="1156" y="649" width="102" height="127" frameX="-7" frameY="-8" frameWidth="113" frameHeight="135"/>
    <SubTexture name="shadow_walk/walk_0041" x="1156" y="520" width="102" height="127" frameX="-6" frameY="-8" frameWidth="113" frameHeight="135"/>
    <SubTexture name="shadow_walk/walk_0042" x="1053" y="391" width="102" height="127" frameX="-6" frameY="-8" frameWidth="113" frameHeight="135"/>
    <SubTexture name="shadow_walk/walk_0043" x="1053" y="262" width="102" height="127" frameX="-6" frameY="-8" frameWidth="113" frameHeight="135"/>
    <SubTexture name="shadow_walk/walk_0044" x="845" y="392" width="102" height="128" frameX="-6" frameY="-7" frameWidth="113" frameHeight="135"/>
    <SubTexture name="shadow_walk/walk_0045" x="845" y="262" width="102" height="128" frameX="-6" frameY="-7" frameWidth="113" frameHeight="135"/>
    <SubTexture name="shadow_walk/walk_0046" x="948" y="2" width="102" height="128" frameX="-6" frameY="-7" frameWidth="113" frameHeight="135"/>
    <SubTexture name="shadow_walk/walk_0047" x="845" y="132" width="102" height="128" frameX="-6" frameY="-7" frameWidth="113" frameHeight="135"/>
    <SubTexture name="shadow_walk/walk_0048" x="846" y="782" width="102" height="128" frameX="-6" frameY="-7" frameWidth="113" frameHeight="135"/>
    <SubTexture name="shadow_walk/walk_0049" x="635" y="132" width="103" height="128" frameX="-5" frameY="-7" frameWidth="113" frameHeight="135"/>
</TextureAtlas>
